dibb/__init__.py
dibb/block_worker.py
dibb/dibb.py
dibb/fitness_evaluator.py
dibb/remote_data.py
dibb/opt_wrappers/__init__.py
dibb/opt_wrappers/cma_ipop_wrapper.py
dibb/opt_wrappers/cma_wrapper.py
dibb/opt_wrappers/lmmaes_wrapper.py
dibb/opt_wrappers/parameter_guessing.py
dibb-0.29.8.dist-info/LICENSE.txt
dibb-0.29.8.dist-info/METADATA
dibb-0.29.8.dist-info/WHEEL
dibb-0.29.8.dist-info/top_level.txt
dibb-0.29.8.dist-info/RECORD
