Metadata-Version: 2.1
Name: dibb
Version: 0.29.8
Summary: DiBB: Distributing Black-Box optimization
Home-page: https://github.com/giuse/dibb
Author: Giuseppe Cuccu
Author-email: giuseppe.cuccu@gmail.com
License: License :: OSI Approved :: MIT License
Keywords: black-box optimization,distributed computation
Requires-Python: >=3.6
License-File: LICENSE.txt
Requires-Dist: numpy
Requires-Dist: ray[default]
Provides-Extra: all
Requires-Dist: lmmaes ; extra == 'all'
Requires-Dist: cma ; extra == 'all'
Provides-Extra: cma
Requires-Dist: cma ; extra == 'cma'
Provides-Extra: lmmaes
Requires-Dist: lmmaes ; extra == 'lmmaes'
